src/mcp_snowflake_server/__init__.py
src/mcp_snowflake_server/db_client.py
src/mcp_snowflake_server/server.py
src/mcp_snowflake_server/write_detector.py
orange_mcp_snowflake_server-0.4.0.dist-info/METADATA
orange_mcp_snowflake_server-0.4.0.dist-info/WHEEL
orange_mcp_snowflake_server-0.4.0.dist-info/entry_points.txt
orange_mcp_snowflake_server-0.4.0.dist-info/licenses/LICENSE
orange_mcp_snowflake_server-0.4.0.dist-info/RECORD
